{
  "greeting": [
    "Hey {name}! Was kann ich für dich tun?",
    "Moin {name}! Wo drückt der Schuh?",
    "Hi {name}, schieß los – was ist kaputt?",
    "Guten {tageszeit} {name}! Was gibt's?",
    "Hey {name}, IT Guru hier – was liegt an?",
    "Servus {name}! Lass hören, was klemmt.",
    "Na {name}, was macht die Technik heute?",
    "Hallo {name}! Bin bereit, dein Problem zu lösen.",
    "Hey {name}! Schön, dass du dich meldest. Was kann ich tun?",
    "Yo {name}, welcher Rechner zickt denn heute rum?",
    "Guten {tageszeit}! Was kann der IT Guru für dich richten?",
    "{name}, sag mir was los ist – ich kümmer mich drum."
  ],
  "problemFound": [
    "Ah, das kenne ich! Das klingt nach: {kategorie}.",
    "Okay, ich glaube ich weiß was los ist. Lass mich kurz schauen...",
    "Das kommt mir bekannt vor – {kategorie} hab ich schon öfter gesehen.",
    "Alles klar, da hab ich was für dich. Klingt nach {kategorie}.",
    "Jap, das hatte ich schon ein paar Mal. {kategorie} – richtig?",
    "Hmm, das riecht nach {kategorie}. Lass uns das mal anschauen.",
    "Ich hab da eine Idee – das könnte {kategorie} sein.",
    "Check, das kenn ich. {kategorie} ist ein Klassiker.",
    "Ah, {kategorie}! Da kann ich helfen.",
    "Okay, ich bin mir ziemlich sicher: das ist {kategorie}. Schauen wir mal."
  ],
  "diagRunning": [
    "Moment, ich check kurz {hostname}...",
    "Läuft! Ich schau mir {hostname} gerade an...",
    "Sekunde, ich taste mich an {hostname} ran...",
    "Diagnose läuft auf {hostname} – gleich hab ich Ergebnisse.",
    "Ich schau mal was {hostname} so macht... einen Moment.",
    "Bin dran! Prüfe gerade {hostname}...",
    "Lass mich kurz auf {hostname} schauen, dauert nicht lang.",
    "Check läuft... {hostname} wird gerade untersucht."
  ],
  "solutionFound": [
    "Hab was gefunden! Hier ist die Lösung:",
    "Okay, das sollte helfen:",
    "Hier kommt die Lösung – probier mal das:",
    "Ich hab's! Versuch mal Folgendes:",
    "Alles klar, das hier sollte dein Problem lösen:",
    "Gefunden! Das ist der Fix:",
    "So, hier ist mein Vorschlag:",
    "Das müsste klappen – hier die Lösung:"
  ],
  "playbookOffer": [
    "Ich hab ein Playbook für dieses Problem. Soll ich es durchlaufen? ({steps} Schritte, ca. {detail})",
    "Dafür gibt's einen automatischen Fix! {steps} Schritte, dauert ungefähr {detail}. Starten?",
    "Hey, ich kann das automatisch fixen! Playbook mit {steps} Schritten bereit. Los geht's?",
    "Gute Nachricht: dafür hab ich ein Playbook. {steps} Schritte, ~{detail}. Soll ich?",
    "Das kann ich automatisieren! Playbook steht bereit ({steps} Schritte). Ausführen?",
    "Ich könnte das Playbook '{detail}' für dich starten. Einverstanden?"
  ],
  "solved": [
    "Top, freut mich! Noch was anderes?",
    "Super, Problem gelöst! Kann ich sonst noch helfen?",
    "Nice, das hätten wir! Noch irgendwas?",
    "Perfekt! Wenn noch was ist, du weißt wo du mich findest.",
    "Läuft! Meld dich wenn's wieder klemmt.",
    "Sauber, das war's dann. Bis zum nächsten Mal!"
  ],
  "followUp": [
    "Betrifft das alle User oder nur einen bestimmten?",
    "Seit wann tritt das Problem auf?",
    "Wurde kürzlich etwas geändert oder installiert?",
    "Passiert das bei jedem Neustart oder nur manchmal?",
    "Kannst du mir den Hostnamen oder die IP geben?",
    "Ist das Problem auf einem bestimmten Rechner oder überall?",
    "Hast du schon einen Neustart versucht?",
    "Gibt es eine Fehlermeldung? Wenn ja, was steht da?",
    "Betrifft das nur {kategorie} oder auch andere Bereiche?",
    "Ist das Problem gerade jetzt oder tritt es nur manchmal auf?"
  ],
  "noResult": [
    "Hmm, dazu hab ich leider nix in meiner Wissensdatenbank. Kannst du mir mehr Details geben?",
    "Das kenne ich so noch nicht. Beschreib mal genauer was passiert.",
    "Darauf hab ich spontan keine Antwort. Erzähl mir mehr!",
    "Das ist mir noch nicht untergekommen. Kannst du's anders beschreiben?",
    "Hmm, schwierig. Dazu find ich nichts. Was genau passiert denn?",
    "Da bin ich überfragt – hilf mir mal mit ein paar mehr Details."
  ],
  "noLust": [
    "Alles klar, dann lass es uns sein lassen. Meld dich wenn du doch noch Hilfe brauchst!",
    "Okay, kein Ding! Ich bin hier wenn du mich brauchst.",
    "Verstanden, dann parke ich das mal. Du weißt wo du mich findest!",
    "Tipp: Davide :D – der kann dir bestimmt auch weiterhelfen. Soll ich ein Ticket aufmachen?",
    "Kein Problem! Tipp: Davide :D – frag den mal, der kennt sich da aus.",
    "Wenn du willst, mach ich dir ein Ticket auf. Tipp: Davide :D der regelt das schon!",
    "Alles klar! Alternativ: Tipp: Davide :D – der hat da bestimmt ne Idee.",
    "Na gut, dann erstell ich mal ein Ticket. Tipp: Davide :D – der kümmert sich drum!"
  ]
}
